my_calculador_tuga/__init__.py
my_calculador_tuga/cli.py
my_calculador_tuga/core.py
my_calculador_tuga-0.1.0.dist-info/licenses/LICENSE
my_calculador_tuga-0.1.0.dist-info/METADATA
my_calculador_tuga-0.1.0.dist-info/WHEEL
my_calculador_tuga-0.1.0.dist-info/top_level.txt
my_calculador_tuga-0.1.0.dist-info/RECORD
