Metadata-Version: 2.4
Name: my_calculador_tuga
Version: 0.1.0
Summary: Uma calculadora simples em Python
Author-email: Geraldo <geraldo.sm.almeida@gmail.com>
License: MIT
Project-URL: Homepage, https://github.com/seuuser/my-calculator
Project-URL: Repository, https://github.com/seuuser/my-calculator
Classifier: Programming Language :: Python :: 3
Classifier: License :: OSI Approved :: MIT License
Classifier: Operating System :: OS Independent
Requires-Python: >=3.8
License-File: LICENSE
Dynamic: license-file
